pytlx/__init__.py
pytlx/token.py
pytlx/utils.py
pytlx-0.1.1.dist-info/LICENSE
pytlx-0.1.1.dist-info/METADATA
pytlx-0.1.1.dist-info/WHEEL
pytlx-0.1.1.dist-info/top_level.txt
pytlx-0.1.1.dist-info/RECORD
